{"code":"0111500000","name":"смт Армянськ (Армянск)","parcels":[{"c":"0111500000:01:002:0202","a":0.2299,"o":"","r":"","ot":"Не визначено","ct":"1.11.3","ad":"","ed":"","ey":null,"rd":"","cn":"","ra":null,"np":null,"re":"","oi":"","oc":0,"od":""},{"c":"0111500000:01:002:0075","a":0.0078,"o":"","r":"","ot":"Не визначено","ct":"для будівництва та обслуговування будівель торгівлі","ad":"","ed":"","ey":null,"rd":"","cn":"","ra":null,"np":null,"re":"","oi":"","oc":0,"od":""},{"c":"0111500000:01:003:0120","a":0.0719,"o":"","r":"","ot":"Не визначено","ct":"для будівництва і обслуговування будівель торгівлі","ad":"","ed":"","ey":null,"rd":"","cn":"","ra":null,"np":null,"re":"","oi":"","oc":0,"od":""},{"c":"0111500000:01:002:0025","a":0.0029,"o":"","r":"","ot":"Не визначено","ct":"03.07 для будівництва та обслуговування будівель торгівлі","ad":"","ed":"","ey":null,"rd":"","cn":"","ra":null,"np":null,"re":"","oi":"","oc":0,"od":""},{"c":"0111500000:01:008:0020","a":0.0373,"o":"","r":"","ot":"Приватна власність","ct":"для будівництва та обслуговування будівель закладів охорони здоров'я та соціальної допомоги","ad":"","ed":"","ey":null,"rd":"","cn":"","ra":null,"np":null,"re":"","oi":"","oc":0,"od":""},{"c":"0111500000:01:008:0014","a":0.0128,"o":"","r":"","ot":"Державна власність","ct":"для будівництва та обслуговування будівель торгівлі","ad":"","ed":"","ey":null,"rd":"","cn":"","ra":null,"np":null,"re":"","oi":"","oc":0,"od":""},{"c":"0111500000:01:002:0077","a":0.002,"o":"","r":"","ot":"Державна власність","ct":"для будівництва та обслуговування будівель торгівлі","ad":"","ed":"","ey":null,"rd":"","cn":"","ra":null,"np":null,"re":"","oi":"","oc":0,"od":""},{"c":"0111500000:01:002:0029","a":0.0311,"o":"","r":"","ot":"Не визначено","ct":"для будівництва та обслуговування будівель торгівлі","ad":"","ed":"","ey":null,"rd":"","cn":"","ra":null,"np":null,"re":"","oi":"","oc":0,"od":""},{"c":"0111500000:02:001:0002","a":4376.4736,"o":"","r":"","ot":"Державна власність","ct":"","ad":"","ed":"","ey":null,"rd":"","cn":"","ra":null,"np":null,"re":"","oi":"","oc":0,"od":""},{"c":"0111500000:01:008:0007","a":0.023,"o":"","r":"","ot":"Приватна власність","ct":"Оптової торгівлі та складського господарства","ad":"","ed":"","ey":null,"rd":"","cn":"","ra":null,"np":null,"re":"","oi":"","oc":0,"od":""},{"c":"0111500000:01:002:0149","a":0.0042,"o":"","r":"","ot":"Державна власність","ct":"03.07 для будівництва та обслуговування будівель торгівлі","ad":"","ed":"","ey":null,"rd":"","cn":"","ra":null,"np":null,"re":"","oi":"","oc":0,"od":""},{"c":"0111500000:01:008:0012","a":0.002,"o":"","r":"","ot":"Не визначено","ct":"для будівництва та обслуговування будівель торгівлі","ad":"","ed":"","ey":null,"rd":"","cn":"","ra":null,"np":null,"re":"","oi":"","oc":0,"od":""},{"c":"0111500000:01:002:0017","a":0.004,"o":"","r":"","ot":"Державна власність","ct":"для будівництва та обслуговування будівель торгівлі","ad":"","ed":"","ey":null,"rd":"","cn":"","ra":null,"np":null,"re":"","oi":"","oc":0,"od":""},{"c":"0111500000:01:003:0620","a":0.1,"o":"","r":"","ot":"Приватна власність","ct":"для будівництва та обслуговування житлового будинку господарських будівель і споруд","ad":"","ed":"","ey":null,"rd":"","cn":"","ra":null,"np":null,"re":"","oi":"","oc":0,"od":""},{"c":"0111500000:01:008:0120","a":0.0017,"o":"","r":"","ot":"Не визначено","ct":"для будівництва та обслуговування будівель торгівлі","ad":"","ed":"","ey":null,"rd":"","cn":"","ra":null,"np":null,"re":"","oi":"","oc":0,"od":""},{"c":"0111500000:01:008:0059","a":0.0909,"o":"","r":"","ot":"Державна власність","ct":"для будівництва та обслуговування будівель торгівлі","ad":"","ed":"","ey":null,"rd":"","cn":"","ra":null,"np":null,"re":"","oi":"","oc":0,"od":""},{"c":"0111500000:01:003:0600","a":0.402,"o":"","r":"","ot":"Не визначено","ct":"03.10 для будівництва та обслуговування будівель риночної інфраструктури","ad":"","ed":"","ey":null,"rd":"","cn":"","ra":null,"np":null,"re":"","oi":"","oc":0,"od":""},{"c":"0111500000:01:002:0024","a":0.0029,"o":"","r":"","ot":"Приватна власність","ct":"03.07 для будівництва та обслуговування будівель торгівлі","ad":"","ed":"","ey":null,"rd":"","cn":"","ra":null,"np":null,"re":"","oi":"","oc":0,"od":""},{"c":"0111500000:01:002:0076","a":0.0012,"o":"","r":"","ot":"Державна власність","ct":"для будівництва та обслуговування будівель торгівлі","ad":"","ed":"","ey":null,"rd":"","cn":"","ra":null,"np":null,"re":"","oi":"","oc":0,"od":""},{"c":"0111500000:01:002:0181","a":0.01,"o":"","r":"","ot":"Не визначено","ct":"для будівництва та обслуговування будівель торгівлі","ad":"","ed":"","ey":null,"rd":"","cn":"","ra":null,"np":null,"re":"","oi":"","oc":0,"od":""},{"c":"0111500000:01:008:0015","a":0.0015,"o":"","r":"","ot":"Не визначено","ct":"для будівництва та обслуговування будівель торгівлі","ad":"","ed":"","ey":null,"rd":"","cn":"","ra":null,"np":null,"re":"","oi":"","oc":0,"od":""},{"c":"0111500000:01:011:0404","a":0.0396,"o":"","r":"","ot":"Приватна власність","ct":"Для ведення особистого селянського господарства","ad":"","ed":"","ey":null,"rd":"","cn":"","ra":null,"np":null,"re":"","oi":"","oc":0,"od":""},{"c":"0111500000:01:003:0589","a":0.0399,"o":"","r":"","ot":"Приватна власність","ct":"03.10 для будівництва та обслуговування будівель риночной інфраструктури","ad":"","ed":"","ey":null,"rd":"","cn":"","ra":null,"np":null,"re":"","oi":"","oc":0,"od":""},{"c":"0111500000:01:003:0020","a":0.003,"o":"","r":"","ot":"Не визначено","ct":"для будівництва та обслуговування будівель торгівлі","ad":"","ed":"","ey":null,"rd":"","cn":"","ra":null,"np":null,"re":"","oi":"","oc":0,"od":""},{"c":"0111500000:01:002:0279","a":0.0072,"o":"","r":"","ot":"Не визначено","ct":"03.07 для будівництва та обслуговування будівель торгівлі","ad":"","ed":"","ey":null,"rd":"","cn":"","ra":null,"np":null,"re":"","oi":"","oc":0,"od":""},{"c":"0111500000:01:002:0065","a":0.003,"o":"","r":"","ot":"Не визначено","ct":"03.07 для будівництва та обслуговування будівель торгівлі","ad":"","ed":"","ey":null,"rd":"","cn":"","ra":null,"np":null,"re":"","oi":"","oc":0,"od":""},{"c":"0111500000:01:002:0147","a":0.0493,"o":"","r":"","ot":"Державна власність","ct":"для будівництва та обслуговування будівель торгівлі","ad":"","ed":"","ey":null,"rd":"","cn":"","ra":null,"np":null,"re":"","oi":"","oc":0,"od":""},{"c":"0111500000:01:001:0050","a":0.1,"o":"","r":"","ot":"Приватна власність","ct":"для будівництва та обслуговування житлового будинку, господарських будівель і споруд (присадибна ділянка)","ad":"","ed":"","ey":null,"rd":"","cn":"","ra":null,"np":null,"re":"","oi":"","oc":0,"od":""},{"c":"0111500000:01:011:0031","a":0.0502,"o":"","r":"","ot":"Державна власність","ct":"для будівництва та обслуговування будівель  торгівлі","ad":"","ed":"","ey":null,"rd":"","cn":"","ra":null,"np":null,"re":"","oi":"","oc":0,"od":""}]}