{"code":"0123580100","name":"с. Степове (Степное)","parcels":[{"c":"0123580100:04:001:0311","a":0.6211,"o":"","r":"","ot":"Державна власність","ct":"Для розміщення, будівництва, експлуатації та обслуговування будівель і споруд об'єктів енергогенеруючих підприємств, установ і організацій","ad":"","ed":"","ey":null,"rd":"","cn":"","ra":null,"np":null,"re":"","oi":"","oc":0,"od":""},{"c":"0123580100:04:001:0326","a":0.21,"o":"","r":"","ot":"Державна власність","ct":"Для розміщення, будівництва, експлуатації та обслуговування будівель і споруд об'єктів енергогенеруючих підприємств, установ і організацій","ad":"","ed":"","ey":null,"rd":"","cn":"","ra":null,"np":null,"re":"","oi":"","oc":0,"od":""},{"c":"0123580100:04:001:0325","a":0.21,"o":"","r":"","ot":"Державна власність","ct":"Для розміщення, будівництва, експлуатації та обслуговування будівель і споруд об'єктів енергогенеруючих підприємств, установ і організацій","ad":"","ed":"","ey":null,"rd":"","cn":"","ra":null,"np":null,"re":"","oi":"","oc":0,"od":""},{"c":"0123580100:04:001:0323","a":0.21,"o":"","r":"","ot":"Державна власність","ct":"Для розміщення, будівництва, експлуатації та обслуговування будівель і споруд об'єктів енергогенеруючих підприємств, установ і організацій","ad":"","ed":"","ey":null,"rd":"","cn":"","ra":null,"np":null,"re":"","oi":"","oc":0,"od":""},{"c":"0123580100:04:001:0316","a":0.21,"o":"","r":"","ot":"Державна власність","ct":"14.01 Для розміщення, будівництва, експлуатації та обслуговування будівель і споруд об'єктів енергогенеруючих підприємств, установ і організацій","ad":"","ed":"","ey":null,"rd":"","cn":"","ra":null,"np":null,"re":"","oi":"","oc":0,"od":""},{"c":"0123580100:04:001:0328","a":0.21,"o":"","r":"","ot":"Державна власність","ct":"Для розміщення, будівництва, експлуатації та обслуговування будівель і споруд об'єктів енергогенеруючих підприємств, установ і організацій","ad":"","ed":"","ey":null,"rd":"","cn":"","ra":null,"np":null,"re":"","oi":"","oc":0,"od":""},{"c":"0123580100:04:001:0319","a":0.21,"o":"","r":"","ot":"Державна власність","ct":"Для розміщення, будівництва, експлуатації та обслуговування будівель і споруд об'єктів енергогенеруючих підприємств, установ і організацій","ad":"","ed":"","ey":null,"rd":"","cn":"","ra":null,"np":null,"re":"","oi":"","oc":0,"od":""},{"c":"0123580100:04:001:0313","a":0.3527,"o":"","r":"","ot":"Державна власність","ct":"Для розміщення, будівництва, експлуатації та обслуговування будівель і споруд об'єктів енергогенеруючих підприємств, установ і організацій","ad":"","ed":"","ey":null,"rd":"","cn":"","ra":null,"np":null,"re":"","oi":"","oc":0,"od":""},{"c":"0123580100:04:001:0322","a":0.21,"o":"","r":"","ot":"Державна власність","ct":"Для розміщення, будівництва, експлуатації та обслуговування будівель і споруд об'єктів енергогенеруючих підприємств, установ і організацій","ad":"","ed":"","ey":null,"rd":"","cn":"","ra":null,"np":null,"re":"","oi":"","oc":0,"od":""},{"c":"0123580100:04:001:0312","a":2.308,"o":"","r":"","ot":"Державна власність","ct":"Для розміщення, будівництва, експлуатації та обслуговування будівель і споруд об'єктів енергогенеруючих підприємств, установ і організацій","ad":"","ed":"","ey":null,"rd":"","cn":"","ra":null,"np":null,"re":"","oi":"","oc":0,"od":""},{"c":"0123580100:04:001:0318","a":0.21,"o":"","r":"","ot":"Державна власність","ct":"Для розміщення, будівництва, експлуатації та обслуговування будівель і споруд об'єктів енергогенеруючих підприємств, установ і організацій","ad":"","ed":"","ey":null,"rd":"","cn":"","ra":null,"np":null,"re":"","oi":"","oc":0,"od":""},{"c":"0123580100:04:001:0314","a":6.0031,"o":"","r":"","ot":"Державна власність","ct":"Для розміщення, будівництва, експлуатації та обслуговування будівель і споруд об'єктів енергогенеруючих підприємств, установ і організацій","ad":"","ed":"","ey":null,"rd":"","cn":"","ra":null,"np":null,"re":"","oi":"","oc":0,"od":""},{"c":"0123580100:04:001:0320","a":0.21,"o":"","r":"","ot":"Державна власність","ct":"Для розміщення, будівництва, експлуатації та обслуговування будівель і споруд об'єктів енергогенеруючих підприємств, установ і організацій","ad":"","ed":"","ey":null,"rd":"","cn":"","ra":null,"np":null,"re":"","oi":"","oc":0,"od":""},{"c":"0123580100:04:001:0327","a":0.21,"o":"","r":"","ot":"Державна власність","ct":"Для розміщення, будівництва, експлуатації та обслуговування будівель і споруд об'єктів енергогенеруючих підприємств, установ і організацій","ad":"","ed":"","ey":null,"rd":"","cn":"","ra":null,"np":null,"re":"","oi":"","oc":0,"od":""},{"c":"0123580100:04:001:0321","a":0.21,"o":"","r":"","ot":"Державна власність","ct":"Для розміщення, будівництва, експлуатації та обслуговування будівель і споруд об'єктів енергогенеруючих підприємств, установ і організацій","ad":"","ed":"","ey":null,"rd":"","cn":"","ra":null,"np":null,"re":"","oi":"","oc":0,"od":""},{"c":"0123580100:04:001:0317","a":0.21,"o":"","r":"","ot":"Державна власність","ct":"Для розміщення, будівництва, експлуатації та обслуговування будівель і споруд об'єктів енергогенеруючих підприємств, установ і організацій","ad":"","ed":"","ey":null,"rd":"","cn":"","ra":null,"np":null,"re":"","oi":"","oc":0,"od":""},{"c":"0123580100:04:001:0324","a":0.21,"o":"","r":"","ot":"Державна власність","ct":"Для розміщення, будівництва, експлуатації та обслуговування будівель і споруд об'єктів енергогенеруючих підприємств, установ і організацій","ad":"","ed":"","ey":null,"rd":"","cn":"","ra":null,"np":null,"re":"","oi":"","oc":0,"od":""},{"c":"0123580100:04:001:0315","a":0.21,"o":"","r":"","ot":"Державна власність","ct":"14.01 Для розміщення, будівництва, експлуатації та обслуговування будівель і споруд об'єктів енергогенеруючих підприємств, установ і організацій","ad":"","ed":"","ey":null,"rd":"","cn":"","ra":null,"np":null,"re":"","oi":"","oc":0,"od":""}]}