{"code":"2323355400","name":"с. Показне (Показное)","parcels":[{"c":"2323355400:05:004:0011","a":4.9198,"o":"","r":"","ot":"Приватна власність","ct":"01.01 для ведення товарного сільськогосподарського виробництва","ad":"","ed":"","ey":null,"rd":"","cn":"","ra":null,"np":null,"re":"","oi":"","oc":0,"od":""},{"c":"2323355400:05:004:0013","a":4.9202,"o":"","r":"","ot":"Приватна власність","ct":"01.01 для ведення товарного сільськогосподарського виробництва","ad":"","ed":"","ey":null,"rd":"","cn":"","ra":null,"np":null,"re":"","oi":"","oc":0,"od":""},{"c":"2323355400:05:002:0010","a":4.9001,"o":"","r":"","ot":"Приватна власність","ct":"01.01 для ведення товарного сільськогосподарського виробництва","ad":"","ed":"","ey":null,"rd":"","cn":"","ra":null,"np":null,"re":"","oi":"","oc":0,"od":""},{"c":"2323355400:05:004:0003","a":4.919,"o":"","r":"","ot":"Приватна власність","ct":"01.01 для ведення товарного сільськогосподарського виробництва","ad":"","ed":"","ey":null,"rd":"","cn":"","ra":null,"np":null,"re":"","oi":"","oc":0,"od":""},{"c":"2323355400:05:002:0005","a":4.9,"o":"","r":"","ot":"Приватна власність","ct":"01.01 для ведення товарного сільськогосподарського виробництва","ad":"","ed":"","ey":null,"rd":"","cn":"","ra":null,"np":null,"re":"","oi":"","oc":0,"od":""},{"c":"2323355400:05:001:0002","a":5.0799,"o":"","r":"","ot":"Приватна власність","ct":"01.01 для ведення товарного сільськогосподарського виробництва","ad":"","ed":"","ey":null,"rd":"","cn":"","ra":null,"np":null,"re":"","oi":"","oc":0,"od":""}]}